{"_ts":[1577846287,1577890116],"_r":{"breakdown":{"html":{"bytes":[5142,5142],"requests":[1,1]},"js":{"bytes":[0,0],"requests":[0,0]},"css":{"bytes":[0,0],"requests":[0,0]},"image":{"bytes":[0,0],"requests":[0,0]},"flash":{"bytes":[0,0],"requests":[0,0]},"font":{"bytes":[0,0],"requests":[0,0]},"video":{"bytes":[0,0],"requests":[0,0]},"other":{"bytes":[0,0],"requests":[0,0]}},"date":[1577846287,1577890116],"domElements":[null,null],"domInteractive":[null,null],"firstPaint":[null,null],"fullyLoaded":[null,null],"id":["200101_P7_8c09fa929cbcbb2e6a5a30f5b89a5b31","200101_WZ_d3785fe989a8453f9033731e30e12233"],"loadTime":[null,null],"render":[null,null],"SpeedIndex":[null,null],"TTFB":[null,null],"videoFrames":[[{"_i":"ms_000000.jpg","_t":0,"_vc":100}],[{"_i":"ms_000000.jpg","_t":0,"_vc":100}]],"visualComplete":[null,null],"lighthouse":[null,null],"pagespeed":[100,100]}}